README.md
setup.py
elastic_lib/__init__.py
elastic_lib/elastic.py
elastic_lib/test_elastic.py
elastic_lib/test_utils.py
elastic_lib/utils.py
elastic_lib.egg-info/PKG-INFO
elastic_lib.egg-info/SOURCES.txt
elastic_lib.egg-info/dependency_links.txt
elastic_lib.egg-info/top_level.txt