Metadata-Version: 2.1
Name: elastic-lib
Version: 24.3.25
Summary: Common elastic stuff for the projects.
Home-page: https://labola.jp
Author: Luxeys
Author-email: tessier@luxeys.com
License: MIT
Platform: UNKNOWN
Classifier: Programming Language :: Python :: 3
Classifier: License :: OSI Approved :: MIT License
Classifier: Operating System :: OS Independent
